<?xml version="1.0" encoding="utf-8" ?>
<ItemManifestConfiguration
    xmlns="http://schemas.microsoft.com/fabric/workload-manifest"
    SchemaVersion="2.0"
    WorkloadName="{{WORKLOAD_NAME}}">

    <Item TypeName="FabInspectorRulesCatalog">
        <DisplayName>FabInspector rules catalog</DisplayName>
        <Description>A curated catalog that references one or more FabInspector rule set items and can run them as a group against the current workspace.</Description>
        <Editor Path="/items/catalog" />
        <JobScheduler>
            <OnDemandJobDeduplicateOptions>PerItem</OnDemandJobDeduplicateOptions>
            <ScheduledJobDeduplicateOptions>PerItem</ScheduledJobDeduplicateOptions>
            <ItemJobTypes>
                <ItemJobType Name="FabInspector.FabInspectorRulesCatalog.RunCatalog" />
            </ItemJobTypes>
        </JobScheduler>
    </Item>

</ItemManifestConfiguration>
